corral/__init__.py
corral/app.py
corral/dev.py
corral/dl.py
corral/error.py
corral/exceptions.py
corral/util.py
corral/templates/base.html
corral/templates/error.html
corral/templates/login.html
corral/templates/success.html
corral/views/__init__.py
corral/views/private.py
corral/views/public.py
corral-1.3.3.dist-info/DESCRIPTION.rst
corral-1.3.3.dist-info/METADATA
corral-1.3.3.dist-info/RECORD
corral-1.3.3.dist-info/WHEEL
corral-1.3.3.dist-info/entry_points.txt
corral-1.3.3.dist-info/metadata.json
corral-1.3.3.dist-info/top_level.txt
