Metadata-Version: 2.0
Name: corral
Version: 1.3.3
Summary: API for downloading files.
Home-page: https://github.com/nickfrostatx/corral
Author: Nick Frost
Author-email: nickfrostatx@gmail.com
License: MIT
Keywords: corral
Platform: UNKNOWN
Classifier: Development Status :: 5 - Production/Stable
Classifier: Framework :: Flask
Classifier: Intended Audience :: Developers
Classifier: License :: OSI Approved :: MIT License
Classifier: Programming Language :: Python :: 2
Classifier: Programming Language :: Python :: 2.6
Classifier: Programming Language :: Python :: 2.7
Classifier: Programming Language :: Python :: 3
Classifier: Programming Language :: Python :: 3.3
Classifier: Programming Language :: Python :: 3.4
Classifier: Programming Language :: Python :: 3.5
Classifier: Programming Language :: Python :: Implementation :: CPython
Classifier: Programming Language :: Python :: Implementation :: PyPy
Requires-Dist: Flask (>=0.10.1)
Requires-Dist: requests (>=2.7.0)
